auth_user_mgr/__init__.py
auth_user_mgr/_api.py
auth_user_mgr/_config.py
auth_user_mgr/_email.py
auth_user_mgr/_helpers.py
auth_user_mgr/_user.py
auth_user_mgr/main.py
auth_user_mgr/templates/invitation.html.j2
authentik_user_manager-1.0.3.dist-info/LICENSE
authentik_user_manager-1.0.3.dist-info/LICENSES/Apache-2.0.txt
authentik_user_manager-1.0.3.dist-info/LICENSES/CC-BY-4.0.txt
authentik_user_manager-1.0.3.dist-info/LICENSES/CC0-1.0.txt
authentik_user_manager-1.0.3.dist-info/METADATA
authentik_user_manager-1.0.3.dist-info/WHEEL
authentik_user_manager-1.0.3.dist-info/entry_points.txt
authentik_user_manager-1.0.3.dist-info/RECORD
