Metadata-Version: 2.3
Name: authentik-user-manager
Version: 1.0.3
Summary: Managing Authentik users via YAML files
License: Apache-2.0
Keywords: authentik,user-management
Author: Max Mehl
Author-email: max.mehl@deutschebahn.com
Requires-Python: >=3.10,<4.0
Classifier: License :: OSI Approved :: Apache Software License
Classifier: Programming Language :: Python :: 3
Classifier: Programming Language :: Python :: 3.10
Classifier: Programming Language :: Python :: 3.11
Classifier: Programming Language :: Python :: 3.12
Classifier: Programming Language :: Python :: 3.13
Requires-Dist: jinja2 (>=3.1.5,<4.0.0)
Requires-Dist: python-slugify (>=8.0.4,<9.0.0)
Requires-Dist: pyyaml (>=6.0.2,<7.0.0)
Requires-Dist: requests (>=2.32.3,<3.0.0)
Project-URL: Repository, https://github.com/OpenRailAssociation/authentik-user-manager
